mahi_gui.cp38-win_amd64.pyd
mahi_gui-0.3.2.dist-info/LICENSE
mahi_gui-0.3.2.dist-info/METADATA
mahi_gui-0.3.2.dist-info/WHEEL
mahi_gui-0.3.2.dist-info/top_level.txt
mahi_gui-0.3.2.dist-info/RECORD
