Metadata-Version: 2.1
Name: mahi-gui
Version: 0.3.2
Summary: Python bindings for mahi-gui imgui and implot.
Home-page: https://github.com/JoelLinn/py-mahi-gui
Author: Joel Linn
Author-email: jl@conductive.de
License: UNKNOWN
Platform: UNKNOWN
